pgvector/asyncpg/__init__.py
pgvector/django/__init__.py
pgvector/django/forms.py
pgvector/django/widgets.py
pgvector/psycopg/__init__.py
pgvector/psycopg2/__init__.py
pgvector/sqlalchemy/__init__.py
pgvector/utils/__init__.py
pgvector-0.2.1.dist-info/LICENSE.txt
pgvector-0.2.1.dist-info/METADATA
pgvector-0.2.1.dist-info/WHEEL
pgvector-0.2.1.dist-info/top_level.txt
pgvector-0.2.1.dist-info/RECORD
