Metadata-Version: 2.1
Name: pgvector
Version: 0.2.1
Summary: pgvector support for Python
Home-page: https://github.com/pgvector/pgvector-python
Author: Andrew Kane
Author-email: andrew@ankane.org
License: MIT
Requires-Python: >=3.8
License-File: LICENSE.txt
Requires-Dist: numpy
